cyberfusion/CoreCli/__init__.py
cyberfusion/CoreCli/_utilities.py
cyberfusion/CoreCli/api_users.py
cyberfusion/CoreCli/basic_authentication_realms.py
cyberfusion/CoreCli/borg.py
cyberfusion/CoreCli/certificate_managers.py
cyberfusion/CoreCli/certificates.py
cyberfusion/CoreCli/clusters.py
cyberfusion/CoreCli/cmses.py
cyberfusion/CoreCli/crons.py
cyberfusion/CoreCli/custom_config_snippets.py
cyberfusion/CoreCli/custom_configs.py
cyberfusion/CoreCli/customers.py
cyberfusion/CoreCli/daemons.py
cyberfusion/CoreCli/databases.py
cyberfusion/CoreCli/domain_routers.py
cyberfusion/CoreCli/firewall_groups.py
cyberfusion/CoreCli/firewall_rules.py
cyberfusion/CoreCli/fpm_pools.py
cyberfusion/CoreCli/ftp_users.py
cyberfusion/CoreCli/haproxy_listens.py
cyberfusion/CoreCli/hosts_entries.py
cyberfusion/CoreCli/htpasswd.py
cyberfusion/CoreCli/logs.py
cyberfusion/CoreCli/mail.py
cyberfusion/CoreCli/main.py
cyberfusion/CoreCli/malwares.py
cyberfusion/CoreCli/mariadb_encryption_keys.py
cyberfusion/CoreCli/nodes.py
cyberfusion/CoreCli/passenger_apps.py
cyberfusion/CoreCli/redis_instances.py
cyberfusion/CoreCli/security_txt_policies.py
cyberfusion/CoreCli/sites.py
cyberfusion/CoreCli/ssh_keys.py
cyberfusion/CoreCli/task_collections.py
cyberfusion/CoreCli/unix_users.py
cyberfusion/CoreCli/url_redirects.py
cyberfusion/CoreCli/virtual_hosts.py
python3_cyberfusion_corectl-3.2.3.dist-info/METADATA
python3_cyberfusion_corectl-3.2.3.dist-info/WHEEL
python3_cyberfusion_corectl-3.2.3.dist-info/entry_points.txt
python3_cyberfusion_corectl-3.2.3.dist-info/top_level.txt
python3_cyberfusion_corectl-3.2.3.dist-info/RECORD
